{
  "properties": [
    {
      "id": 1,
      "title": "Commercial Office Space",
      "location": "Electronic City, Bangalore",
      "price": "₹2,50,00,000",
      "type": "Commercial",
      "bedrooms": 0,
      "bathrooms": 2,
      "area": "3000 sq ft",
      "image": "/images/site.jpg",
      "featured": true,
      "description": "Premium office space in Electronic City with excellent connectivity and parking facilities.",
      "features": ["Parking Space", "Security", "Lift", "Power Backup", "Internet Ready", "Conference Room"],
      "amenities": ["24/7 Security", "Power Backup", "Internet Ready", "Parking", "Lift"],
      "dimensions": "3000 sq ft",
      "status": "Available",
      "possession": "Ready to Move",
      "furnishing": "Unfurnished"
    },
    {
      "id": 2,
      "title": "Retail Shop Space",
      "location": "Indiranagar, Bangalore",
      "price": "₹1,80,00,000",
      "type": "Commercial",
      "bedrooms": 0,
      "bathrooms": 1,
      "area": "1200 sq ft",
      "image": "/images/property1.jpg",
      "featured": false,
      "description": "High-footfall retail space in prime Indiranagar location with excellent business potential.",
      "features": ["High Footfall", "Parking", "Security", "Power Backup", "Good Visibility"],
      "amenities": ["Power Backup", "Water Supply", "Internet Ready", "Parking", "Security"],
      "dimensions": "1200 sq ft",
      "status": "Available",
      "possession": "Ready to Move",
      "furnishing": "Unfurnished"
    },
    {
      "id": 3,
      "title": "Warehouse Space",
      "location": "Peenya Industrial Area, Bangalore",
      "price": "₹3,20,00,000",
      "type": "Commercial",
      "bedrooms": 0,
      "bathrooms": 2,
      "area": "5000 sq ft",
      "image": "/images/plot.jpg",
      "featured": false,
      "description": "Large warehouse space in Peenya Industrial Area with loading facilities.",
      "features": ["Loading Dock", "High Ceiling", "Security", "Power Backup", "Parking", "Office Space"],
      "amenities": ["Power Backup", "Water Supply", "Internet Ready", "Loading Dock", "Security"],
      "dimensions": "5000 sq ft",
      "status": "Available",
      "possession": "Ready to Move",
      "furnishing": "Unfurnished"
    },
    {
      "id": 4,
      "title": "Residential Plot - 30x40",
      "location": "Whitefield, Bangalore",
      "price": "₹75,00,000",
      "type": "Plot",
      "bedrooms": 0,
      "bathrooms": 0,
      "area": "1200 sq ft",
      "image": "/images/property1.jpg",
      "featured": false,
      "description": "Prime residential plot in Whitefield with excellent connectivity and development potential.",
      "features": ["Corner Plot", "Road Access", "Water Supply", "Power Connection", "Good Soil", "Clear Title"],
      "amenities": ["Road Access", "Water Supply", "Power Connection", "Clear Title", "Approved Layout"],
      "dimensions": "30x40 ft",
      "status": "Available",
      "possession": "Ready for Construction",
      "furnishing": "Unfurnished"
    },
    {
      "id": 5,
      "title": "Luxury Villa Plot - 50x80",
      "location": "Sarjapur Road, Bangalore",
      "price": "₹2,50,00,000",
      "type": "Plot",
      "bedrooms": 0,
      "bathrooms": 0,
      "area": "4000 sq ft",
      "image": "/images/property2.jpg",
      "featured": false,
      "description": "Premium villa plot in exclusive gated community with all amenities and security.",
      "features": ["Gated Community", "Corner Plot", "Road Access", "Water Supply", "Power Connection", "Security", "Garden Area"],
      "amenities": ["Road Access", "Water Supply", "Power Connection", "Security", "Garden Area", "Clear Title"],
      "dimensions": "50x80 ft",
      "status": "Available",
      "possession": "Ready for Construction",
      "furnishing": "Unfurnished"
    }
  ],
  "propertyTypes": [
    "Apartment",
    "Villa", 
    "Commercial",
    "Plot",
    "Penthouse",
    "Studio"
  ],
  "locations": [
    "Whitefield, Bangalore",
    "Sarjapur Road, Bangalore",
    "Electronic City, Bangalore",
    "HSR Layout, Bangalore",
    "Indiranagar, Bangalore",
    "Yelahanka, Bangalore",
    "Koramangala, Bangalore",
    "Peenya Industrial Area, Bangalore",
    "Bellandur, Bangalore",
    "Manyata Tech Park, Bangalore",
    "Marathahalli, Bangalore",
    "Bannerghatta Road, Bangalore"
  ]
}
